odoo/addons/edi_state_oca/README.rst
odoo/addons/edi_state_oca/__init__.py
odoo/addons/edi_state_oca/__manifest__.py
odoo/addons/edi_state_oca/i18n/edi_state_oca.pot
odoo/addons/edi_state_oca/models/__init__.py
odoo/addons/edi_state_oca/models/edi_exchange_type.py
odoo/addons/edi_state_oca/models/edi_state.py
odoo/addons/edi_state_oca/models/edi_state_consumer_mixin.py
odoo/addons/edi_state_oca/models/edi_state_workflow.py
odoo/addons/edi_state_oca/readme/CONFIGURE.rst
odoo/addons/edi_state_oca/readme/CONTRIBUTORS.rst
odoo/addons/edi_state_oca/readme/DESCRIPTION.rst
odoo/addons/edi_state_oca/readme/ROADMAP.rst
odoo/addons/edi_state_oca/readme/USAGE.rst
odoo/addons/edi_state_oca/security/ir_model_access.xml
odoo/addons/edi_state_oca/static/description/icon.png
odoo/addons/edi_state_oca/static/description/index.html
odoo/addons/edi_state_oca/tests/__init__.py
odoo/addons/edi_state_oca/tests/fake_models.py
odoo/addons/edi_state_oca/tests/test_edi_state.py
odoo/addons/edi_state_oca/views/edi_exchange_type.xml
odoo/addons/edi_state_oca/views/edi_state.xml
odoo/addons/edi_state_oca/views/edi_state_workflow.xml
odoo/addons/edi_state_oca/views/menuitems.xml
odoo14_addon_edi_state_oca-14.0.1.0.2.dist-info/METADATA
odoo14_addon_edi_state_oca-14.0.1.0.2.dist-info/WHEEL
odoo14_addon_edi_state_oca-14.0.1.0.2.dist-info/top_level.txt
odoo14_addon_edi_state_oca-14.0.1.0.2.dist-info/RECORD
