Metadata-Version: 2.1
Name: odoo14-addon-edi-state-oca
Version: 14.0.1.0.2
Summary: Allow to assign specific EDI states to related records.
Home-page: https://github.com/OCA/edi-framework
Author: Camptocamp, Odoo Community Association (OCA)
Author-email: support@odoo-community.org
License: LGPL-3
Platform: UNKNOWN
Classifier: Programming Language :: Python
Classifier: Framework :: Odoo
Classifier: Framework :: Odoo :: 14.0
Classifier: License :: OSI Approved :: GNU Lesser General Public License v3 (LGPLv3)
Classifier: Development Status :: 3 - Alpha
Requires-Python: >=3.6
Requires-Dist: odoo14-addon-edi-oca
Requires-Dist: odoo <14.1dev,>=14.0a
